convert_lqm_to_json/__init__.py
convert_lqm_to_json/cli.py
convert_lqm_to_json/memos.py
convert_lqm_to_json/paths.py
convert_lqm_to_json-0.1.15.dist-info/entry_points.txt
convert_lqm_to_json-0.1.15.dist-info/WHEEL
convert_lqm_to_json-0.1.15.dist-info/METADATA
convert_lqm_to_json-0.1.15.dist-info/RECORD
