Metadata-Version: 2.1
Name: convert-lqm-to-json
Version: 0.1.15
Summary: Convert LG QuickMemo+ files into single, text-only JSON file
Home-page: https://github.com/movecodemove/convert-lqm-to-json
License: MIT
Author: Scott Steven Rodriguez
Author-email: scott@movecodemove.com
Requires-Python: >=3.7,<4.0
Classifier: License :: OSI Approved :: MIT License
Classifier: Programming Language :: Python :: 3
Classifier: Programming Language :: Python :: 3.7
Classifier: Programming Language :: Python :: 3.8
Classifier: Programming Language :: Python :: 3.9
Project-URL: Repository, https://github.com/movecodemove/convert-lqm-to-json
